{
  "name": "",
  "scale": 1,
  "stroke": 0,
  "shapes": [
    {
      "x": 247,
      "y": 249,
      "width": "57.7",
      "height": "57.7",
      "rotation": 0,
      "sides": 3,
      "color": {
        "r": 255,
        "g": 0,
        "b": 0,
        "a": 1
      },
      "altColor": {
        "r": 255,
        "g": 255,
        "b": 255,
        "a": 1
      }
    },
    {
      "x": 247,
      "y": 191.3,
      "width": "57.7",
      "height": "57.7",
      "rotation": 180,
      "sides": 3,
      "color": {
        "r": 0,
        "g": 255,
        "b": 0,
        "a": 1
      },
      "altColor": {
        "r": 255,
        "g": 255,
        "b": 255,
        "a": 1
      }
    },
    {
      "x": 178.70904408136,
      "y": 151.89850648875,
      "width": "70.7",
      "height": "70.7",
      "rotation": 75,
      "sides": 4,
      "color": {
        "r": 255,
        "g": 255,
        "b": 0,
        "a": 1
      },
      "altColor": {
        "r": 255,
        "g": 255,
        "b": 255,
        "a": 1
      }
    },
    {
      "x": 315.29095591864,
      "y": 288.40149351125,
      "width": "70.7",
      "height": "70.7",
      "rotation": 75,
      "sides": 4,
      "color": {
        "r": 255,
        "g": 255,
        "b": 0,
        "a": 1
      },
      "altColor": {
        "r": 255,
        "g": 255,
        "b": 255,
        "a": 1
      }
    },
    {
      "x": 315.29095591864,
      "y": 151.89850648875,
      "width": "70.7",
      "height": "70.7",
      "rotation": 15,
      "sides": 4,
      "color": {
        "r": 0,
        "g": 255,
        "b": 255,
        "a": 1
      },
      "altColor": {
        "r": 255,
        "g": 255,
        "b": 255,
        "a": 1
      }
    },
    {
      "x": 354.66966579836,
      "y": 220.15,
      "width": "57.7",
      "height": "57.7",
      "rotation": 90,
      "sides": 3,
      "color": {
        "r": 0,
        "g": 0,
        "b": 255,
        "a": 1
      },
      "altColor": {
        "r": 255,
        "g": 255,
        "b": 255,
        "a": 1
      }
    },
    {
      "x": 412.43191183727,
      "y": 220.13332122414,
      "width": "57.7",
      "height": "57.7",
      "rotation": -90,
      "sides": 3,
      "color": {
        "r": 255,
        "g": 0,
        "b": 255,
        "a": 1
      },
      "altColor": {
        "r": 255,
        "g": 255,
        "b": 255,
        "a": 1
      }
    },
    {
      "x": 451.87286775591,
      "y": 151.89850648875,
      "width": "70.7",
      "height": "70.7",
      "rotation": 75,
      "sides": 4,
      "color": {
        "r": 255,
        "g": 255,
        "b": 0,
        "a": 1
      },
      "altColor": {
        "r": 255,
        "g": 255,
        "b": 255,
        "a": 1
      }
    },
    {
      "x": 383.51966579836,
      "y": 112.48033420164,
      "width": "57.7",
      "height": "57.7",
      "rotation": 0,
      "sides": 3,
      "color": {
        "r": 255,
        "g": 0,
        "b": 0,
        "a": 1
      },
      "altColor": {
        "r": 255,
        "g": 255,
        "b": 255,
        "a": 1
      }
    }
  ],
  "lights": [
    {
      "x": 557,
      "y": 82,
      "color": {
        "r": 255,
        "g": 255,
        "b": 255,
        "a": 1
      },
      "distance": 1200
    },
    {
      "x": 216,
      "y": 351,
      "color": {
        "r": 255,
        "g": 255,
        "b": 255,
        "a": 1
      },
      "distance": 1000
    }
  ],
  "graph": [],
  "backgroundColor": {
    "r": 0,
    "g": 0,
    "b": 0,
    "a": 1
  },
  "ambientColor": {
    "r": 0,
    "g": 0,
    "b": 63,
    "a": 1
  },
  "shadowColor": {
    "r": 127,
    "g": 127,
    "b": 127,
    "a": 0.5
  },
  "shadowOffset": {
  	"x": 2.5,
  	"y": -2.5
  }
}
